mkinf/__init__.py
mkinf/mkinf.py
mkinf/hub/__init__.py
mkinf/hub/pull.py
mseep_mkinf-0.1.9.dist-info/licenses/LICENSE
mseep_mkinf-0.1.9.dist-info/METADATA
mseep_mkinf-0.1.9.dist-info/WHEEL
mseep_mkinf-0.1.9.dist-info/top_level.txt
mseep_mkinf-0.1.9.dist-info/RECORD
